setup.cfg
setup.py
mltools/__init__.py
mltools/data_extractors.py
mltools/features.py
mltools/geojson_tools.py
mltools.egg-info/PKG-INFO
mltools.egg-info/SOURCES.txt
mltools.egg-info/dependency_links.txt
mltools.egg-info/not-zip-safe
mltools.egg-info/requires.txt
mltools.egg-info/top_level.txt