Metadata-Version: 1.0
Name: mltools
Version: 1.1.0
Summary: Removed obsolete crowdsourcing module.
Home-page: https://github.com/kostasthebarbarian/mltools
Author: Kostas Stamatiou
Author-email: kostas.stamatiou@digitalglobe.com
License: MIT
Platform: UNKNOWN
